[
  {
    "title": "Cortex Animated",
    "url": "https://www.youtube.com/playlist?list=PLQ71hYrPwym_fuFZo9WniY_diFm1dM08b",
    "rss": "https://www.youtube.com/feeds/videos.xml?playlist_id=PLQ71hYrPwym_fuFZo9WniY_diFm1dM08b",
    "category": "entertainment"
  },
  {
    "title": "JS Power Hour",
    "url": "http://www.jspowerhour.com/",
    "rss": "https://www.jspowerhour.com/comics.rss",
    "category": "comic"
  },
  {
    "title": "Hot Ones",
    "url": "https://www.youtube.com/playlist?list=PLAzrgbu8gEMIIK3r4Se1dOZWSZzUSadfZ",
    "rss": "https://www.youtube.com/feeds/videos.xml?playlist_id=PLAzrgbu8gEMIIK3r4Se1dOZWSZzUSadfZ",
    "category": "entertainment"
  },
  {
    "title": "Hyperbole and a Half",
    "url": "http://hyperboleandahalf.blogspot.com/",
    "rss": "http://feeds.feedburner.com/Hyperbole-and-a-half",
    "category": "entertainment"
  },
  {
    "title": "Overreacted",
    "url": "https://overreacted.io/",
    "rss": "https://overreacted.io/rss.xml",
    "category": "development"
  },
  {
    "title": "Fun Fact",
    "url": "http://www.funfactcomics.com/",
    "rss": "http://www.funfactcomics.com/rss",
    "category": "comic"
  },
  {
    "title": "Ethan Marcotte",
    "url": "https://ethanmarcotte.com/",
    "rss": "https://ethanmarcotte.com/wrote/feed.xml",
    "category": "development"
  },
  {
    "title": "A List Apart",
    "url": "https://alistapart.com/",
    "rss": "https://alistapart.com/main/feed/",
    "category": "development"
  },
  {
    "title": "Things in Squares",
    "url": "https://www.thingsinsquares.com/",
    "rss": "https://www.thingsinsquares.com/feed/",
    "category": "comic"
  },
  {
    "title": "Panic Blog",
    "url": "https://panic.com/blog",
    "rss": "https://panic.com/blog/feed/",
    "category": "development"
  },
  {
    "title": "Justin O'Beirne",
    "url": "https://www.justinobeirne.com/",
    "rss": "https://www.justinobeirne.com/rss?format=rss",
    "category": "technology"
  },
  {
    "title": "5ish",
    "url": "https://5ish.org/",
    "rss": "https://5ish.org/feed/",
    "category": "entertainment"
  },
  {
    "title": "Hypercritical",
    "url": "http://hypercritical.co/",
    "rss": "http://hypercritical.co/feeds/main",
    "category": "entertainment"
  },
  {
    "title": "The Perry Bible Fellowship",
    "url": "https://pbfcomics.com",
    "rss": "https://pbfcomics.com/feed/",
    "category": "comic"
  },
  {
    "title": "Lil Char and the Gang",
    "url": "https://www.webtoons.com/en/challenge/lil-char-and-the-gang-a-pokemon-parody-series/list?title_no=154745",
    "rss": "https://www.webtoons.com/en/challenge/lil-char-and-the-gang-a-pokemon-parody-series/rss?title_no=154745",
    "category": "comic"
  },
  {
    "title": "Jake Archibald",
    "url": "https://jakearchibald.com/",
    "rss": "https://jakearchibald.com/posts.rss",
    "category": "development"
  },
  {
    "title": "CommitStrip",
    "url": "http://www.commitstrip.com/",
    "rss": "http://www.commitstrip.com/en/feed/",
    "category": "comic"
  },
  {
    "title": "And now it’s all this",
    "url": "http://www.leancrew.com/all-this/",
    "rss": "https://leancrew.com/all-this/feed/",
    "category": "development"
  },
  {
    "title": "What If?",
    "url": "https://what-if.xkcd.com/",
    "rss": "https://what-if.xkcd.com/feed.atom",
    "category": "science"
  },
  {
    "title": "Josh Comeau",
    "url": "https://joshwcomeau.com/",
    "rss": "https://joshwcomeau.com/rss.xml",
    "category": "development"
  },
  {
    "title": "Marco Arment",
    "url": "https://marco.org/",
    "rss": "https://marco.org/rss",
    "category": "entertainment"
  },
  {
    "title": "Catana",
    "url": "https://catanacomics.com/",
    "rss": "https://catanacomics.com/feed/",
    "category": "comic"
  },
  {
    "title": "Good Bear",
    "url": "https://goodbearcomics.com",
    "rss": "https://goodbearcomics.com/feed/",
    "category": "comic"
  },
  {
    "title": "MonkeyUser",
    "url": "https://www.monkeyuser.com/",
    "rss": "https://www.monkeyuser.com/feed.xml",
    "category": "comic"
  },
  {
    "title": "500is Words",
    "url": "https://500ish.com/",
    "rss": "https://500ish.com/feed/",
    "category": "entertainment"
  },
  {
    "title": "The Other End",
    "url": "http://www.kohney.com",
    "rss": "http://www.kohney.com/feed/",
    "category": "comic"
  },
  {
    "title": "Shen Comix",
    "url": "https://shencomix.tumblr.com/",
    "rss": "https://shencomix.tumblr.com/rss",
    "category": "comic"
  },
  {
    "title": "MacStories",
    "url": "https://www.macstories.net/",
    "rss": "https://www.macstories.net/feed/",
    "category": "technology"
  },
  {
    "title": "Two-Bit History",
    "url": "https://twobithistory.org/",
    "rss": "https://twobithistory.org/feed.xml",
    "category": "development"
  },
  {
    "title": "Oglaf",
    "url": "https://www.oglaf.com/latest/",
    "rss": "https://www.oglaf.com/feeds/rss/",
    "category": "comic"
  },
  {
    "title": "Wait But Why",
    "url": "https://waitbutwhy.com",
    "rss": "https://waitbutwhy.com/feed",
    "category": "science"
  },
  {
    "title": "xkcd",
    "url": "https://xkcd.com/",
    "rss": "https://xkcd.com/rss.xml",
    "category": "comic"
  },
  {
    "title": "Andy Bell",
    "url": "https://andy-bell.design/",
    "rss": "https://andy-bell.design/feed/all.xml",
    "category": "development"
  },
  {
    "title": "Poorly Drawn Lines",
    "url": "http://www.poorlydrawnlines.com/",
    "rss": "http://www.poorlydrawnlines.com/feed/",
    "category": "comic"
  },
  {
    "title": "Bodies",
    "url": "https://m.webtoons.com/en/challenge/bodies/list?title_no=313877",
    "rss": "https://www.webtoons.com/en/challenge/bodies/rss?title_no=313877",
    "category": "comic"
  },
  {
    "title": "CSS-Tricks",
    "url": "https://css-tricks.com/",
    "rss": "http://feeds.feedburner.com/CssTricks",
    "category": "development"
  },
  {
    "title": "Port Sherry",
    "url": "http://portsherry.com/",
    "rss": "http://portsherry.com/feed/",
    "category": "comic"
  },
  {
    "title": "Liss is More",
    "url": "https://www.caseyliss.com/",
    "rss": "https://www.caseyliss.com/rss",
    "category": "entertainment"
  },
  {
    "title": "Ash Furrow",
    "url": "https://ashfurrow.com/",
    "rss": "https://feed.ashfurrow.com/feed.xml",
    "category": "entertainment"
  },
  {
    "title": "The History of the Web",
    "url": "https://thehistoryoftheweb.com",
    "rss": "https://thehistoryoftheweb.com/feed/",
    "category": "development"
  },
  {
    "title": "Alligator",
    "url": "https://alligator.io/",
    "rss": "https://alligator.io/feed.xml",
    "category": "development"
  },
  {
    "title": "Saturday Morning Breakfast Cereal",
    "url": "https://www.smbc-comics.com/",
    "rss": "https://www.smbc-comics.com/comic/rss",
    "category": "comic"
  },
  {
    "title": "Surma",
    "url": "https://dassur.ma/",
    "rss": "https://dassur.ma/index.xml",
    "category": "development"
  },
  {
    "title": "The Oatmeal",
    "url": "http://theoatmeal.com/",
    "rss": "https://feeds.feedburner.com/oatmealfeed",
    "category": "comic"
  },
  {
    "title": "Dave Rupert",
    "url": "http://daverupert.com/",
    "rss": "https://daverupert.com/atom.xml",
    "category": "development"
  },
  {
    "title": "The Burger Show",
    "url": "https://www.youtube.com/playlist?list=PLAzrgbu8gEMK8zGcsu70ju7KvWyNBWYnL",
    "rss": "https://www.youtube.com/feeds/videos.xml?playlist_id=PLAzrgbu8gEMJe0ZOKPLRgEc-sp4cLmtz6",
    "category": "entertainment"
  },
  {
    "title": "They Can't Talk",
    "url": "https://theycantalk.com/",
    "rss": "https://theycantalk.com/rss",
    "category": "comic"
  },
  {
    "title": "Movies with Mikey",
    "url": "https://www.youtube.com/playlist?list=PLdGl5mi0XeW2iK2sVp2ni_VDRKrmfF_-Z",
    "rss": "https://www.youtube.com/feeds/videos.xml?playlist_id=PLdGl5mi0XeW2iK2sVp2ni_VDRKrmfF_-Z",
    "category": "entertainment"
  }
]
